nat/meta/pypi.md
nat/plugins/llama_index/__init__.py
nat/plugins/llama_index/embedder.py
nat/plugins/llama_index/llm.py
nat/plugins/llama_index/register.py
nat/plugins/llama_index/tool_wrapper.py
nvidia_nat_llama_index-1.3.1.dist-info/licenses/LICENSE-3rd-party.txt
nvidia_nat_llama_index-1.3.1.dist-info/licenses/LICENSE.md
nvidia_nat_llama_index-1.3.1.dist-info/METADATA
nvidia_nat_llama_index-1.3.1.dist-info/WHEEL
nvidia_nat_llama_index-1.3.1.dist-info/entry_points.txt
nvidia_nat_llama_index-1.3.1.dist-info/top_level.txt
nvidia_nat_llama_index-1.3.1.dist-info/RECORD
