Metadata-Version: 2.4
Name: nvidia-nat-llama-index
Version: 1.3.1
Summary: Subpackage for Llama-Index integration in NeMo Agent toolkit
Author: NVIDIA Corporation
Maintainer: NVIDIA Corporation
License: Apache-2.0
Project-URL: documentation, https://docs.nvidia.com/nemo/agent-toolkit/latest/
Project-URL: source, https://github.com/NVIDIA/NeMo-Agent-Toolkit
Keywords: ai,rag,agents
Classifier: Programming Language :: Python
Classifier: Programming Language :: Python :: 3.11
Classifier: Programming Language :: Python :: 3.12
Classifier: Programming Language :: Python :: 3.13
Requires-Python: <3.14,>=3.11
License-File: LICENSE-3rd-party.txt
License-File: LICENSE.md
Requires-Dist: nvidia-nat==v1.3.1
Requires-Dist: llama-index-core~=0.12.21
Requires-Dist: llama-index-embeddings-azure-openai~=0.3.9
Requires-Dist: llama-index-embeddings-nvidia~=0.3.1
Requires-Dist: llama-index-embeddings-openai~=0.3.1
Requires-Dist: llama-index-llms-azure-openai~=0.3.2
Requires-Dist: llama-index-llms-bedrock~=0.3.8
Requires-Dist: llama-index-llms-litellm~=0.5.1
Requires-Dist: llama-index-llms-nvidia~=0.3.1
Requires-Dist: llama-index-llms-openai~=0.3.42
Requires-Dist: llama-index-readers-file~=0.4.4
Requires-Dist: llama-index~=0.12.21
Dynamic: license-file
